[

  {
    "name": "WIZARD_GLOBAL_METRICS",
    "defaultAggregate": "AVG",
    "defaultResolutionMS": 1000,
    "description": "Total WGME",
    "displayName": "Total WGME",
    "displayNameShort": "Total WGME",
    "isDisabled": 0,
    "unit": "number"
  },
   {
    "name": "WIZARD_GLOBAL_MEASUREMENTS",
    "defaultAggregate": "AVG",
    "defaultResolutionMS": 1000,
    "description": "Total WGM",
    "displayName": "Total WGM",
    "displayNameShort": "Total WGM",
    "isDisabled": 0,
    "unit": "number"
  },
 
]
